jarbas_hive_mind_red
