Metadata-Version: 1.0
Name: jarbas-hive-mind-red
Version: 0.1.6
Summary: Mycroft Node Red
Home-page: https://github.com/OpenJarbas/HiveMind-NodeRed
Author: jarbasAI
Author-email: jarbasai@mailfence.com
License: MIT
Platform: UNKNOWN
